{
  "hash": "f1d3d81eeb5540167668bf71aebc6749",
  "result": {
    "markdown": "# Sensitivity analysis\n\n## Quantitative bias analyses\n\n\n\n\n::: {.cell}\n\n```{.r .cell-code}\nrnorm(5)\n```\n\n::: {.cell-output .cell-output-stdout}\n\n```\n[1] -0.6136 -0.3190  0.7672  0.3058  0.4258\n```\n\n\n:::\n:::\n\n\n## Tipping point analyses\n",
    "supporting": [
      "chapter-18_files"
    ],
    "filters": [
      "rmarkdown/pagebreak.lua"
    ],
    "includes": {},
    "engineDependencies": {},
    "preserve": {},
    "postProcess": true
  }
}